oak_cli/__init__.py
oak_cli/addons/__init__.py
oak_cli/addons/flops/SLAs/__init__.py
oak_cli/addons/flops/SLAs/common.py
oak_cli/addons/flops/SLAs/legacy/cifar10_keras.json
oak_cli/addons/flops/SLAs/legacy/cifar10_pytorch.json
oak_cli/addons/flops/SLAs/legacy/cifar10_simple.json
oak_cli/addons/flops/SLAs/main.py
oak_cli/addons/flops/SLAs/mocks/mnist_multi.json
oak_cli/addons/flops/SLAs/mocks/mnist_simple.json
oak_cli/addons/flops/SLAs/projects/hierarchical_mnist_sklearn_large.json
oak_cli/addons/flops/SLAs/projects/hierarchical_mnist_sklearn_small.json
oak_cli/addons/flops/SLAs/projects/mnist_sklearn_large.json
oak_cli/addons/flops/SLAs/projects/mnist_sklearn_small.json
oak_cli/addons/flops/__init__.py
oak_cli/addons/flops/auxiliary.py
oak_cli/addons/flops/main.py
oak_cli/addons/main.py
oak_cli/ansible/__init__.py
oak_cli/ansible/ansible.cfg
oak_cli/ansible/inventories/group_vars/all.yml
oak_cli/ansible/playbooks/evaluate_resources.yml
oak_cli/ansible/playbooks/install_fundamentals.yml
oak_cli/ansible/python_utils.py
oak_cli/ansible/roles/clear_root_orchestrator/meta/argument_specs.yml
oak_cli/ansible/roles/clear_root_orchestrator/tasks/main.yml
oak_cli/ansible/roles/clear_worker_node/meta/argument_specs.yml
oak_cli/ansible/roles/clear_worker_node/tasks/main.yml
oak_cli/ansible/roles/evaluate_resources/tasks/clear_components.yml
oak_cli/ansible/roles/evaluate_resources/tasks/handle_evaluation_run.yml
oak_cli/ansible/roles/evaluate_resources/tasks/main.yml
oak_cli/ansible/roles/evaluate_resources/tasks/perform_evaluation_run.yml
oak_cli/ansible/roles/prepare_oak_cli/tasks/main.yml
oak_cli/ansible/roles/set_venv_vars/tasks/main.yml
oak_cli/apps/__init__.py
oak_cli/apps/auxiliary.py
oak_cli/apps/common.py
oak_cli/apps/main.py
oak_cli/apps/prepared_SLAs/__init__.py
oak_cli/apps/prepared_SLAs/blank_app_without_services.json
oak_cli/apps/prepared_SLAs/default_app_with_services.json
oak_cli/apps/prepared_SLAs/edge_gaming.json
oak_cli/apps/prepared_SLAs/main.py
oak_cli-0.5.4.dist-info/METADATA
oak_cli-0.5.4.dist-info/WHEEL
oak_cli-0.5.4.dist-info/entry_points.txt
oak_cli-0.5.4.dist-info/RECORD
