Metadata-Version: 2.3
Name: oak_cli
Version: 0.5.4
Summary: The Oakestra CLI
Author: Alexander Malyuk
Author-email: malyuk.alexander1999@gmail.com
Requires-Python: >=3.10,<4.0
Classifier: Programming Language :: Python :: 3
Classifier: Programming Language :: Python :: 3.10
Classifier: Programming Language :: Python :: 3.11
Classifier: Programming Language :: Python :: 3.12
Classifier: Programming Language :: Python :: 3.13
Requires-Dist: ansible (>=10.1.0,<11.0.0)
Requires-Dist: ansible-core (>=2.17.1,<3.0.0)
Requires-Dist: ansible-runner (>=2.4.0,<3.0.0)
Requires-Dist: icecream (>=2.1.3,<3.0.0)
Requires-Dist: oakestra-utils (>=0.2.0,<0.3.0)
Requires-Dist: psutil (>=5.9.8,<6.0.0)
Requires-Dist: pydantic (>=2.6.4,<3.0.0)
Requires-Dist: requests (>=2.32.3,<3.0.0)
Requires-Dist: rich-pixels (>=3.0.1,<4.0.0)
Requires-Dist: typer (>=0.15.4,<0.16.0)
